wltr_doc_validate/BaseDoc.py
wltr_doc_validate/CNH.py
wltr_doc_validate/CNPJ.py
wltr_doc_validate/CNS.py
wltr_doc_validate/CPF.py
wltr_doc_validate/PIS.py
wltr_doc_validate/RGSSP.py
wltr_doc_validate/TituloEleitoral.py
wltr_doc_validate/__init__.py
wltr_doc_validate-1.0.0.dist-info/LICENSE
wltr_doc_validate-1.0.0.dist-info/METADATA
wltr_doc_validate-1.0.0.dist-info/WHEEL
wltr_doc_validate-1.0.0.dist-info/top_level.txt
wltr_doc_validate-1.0.0.dist-info/RECORD
