Metadata-Version: 2.1
Name: wltr-doc-validate
Version: 1.0.0
Summary: Wltr Doc Validate
Home-page: https://github.com/walteravelino/wltr-doc-validate
Author: Walter José Avelino da Silva
Author-email: walter.avelin@gmail.com
License: UNKNOWN
Platform: UNKNOWN
Classifier: Programming Language :: Python :: 3
Classifier: License :: OSI Approved :: MIT License
Classifier: Operating System :: OS Independent
